{"cameraMode":{"drawMode":0,"name":"Shaded","section":"Shading Mode"},"sceneLighting":true,"audioPlay":false,"sceneViewState":{"showFog":true,"showMaterialUpdate":false,"showSkybox":true,"showFlares":true,"showImageEffects":true,"showParticleSystems":true},"in2DMode":false,"pivot":{"x":13.099621772766114,"y":12.110187530517579,"z":5.290428161621094},"rotation":{"x":0.0592956505715847,"y":0.8420668840408325,"z":-0.09462063759565354,"w":0.5276944041252136},"size":54.7014274597168,"orthographic":false}